LICENSE
README.md
setup.py
mogp/__init__.py
mogp/allocmodel.py
mogp/mogp_constrained.py
mogp/neg_linear.py
mogp/obsmodel.py
mogp/test_package.py
mogp/utils.py
mogptw.egg-info/PKG-INFO
mogptw.egg-info/SOURCES.txt
mogptw.egg-info/dependency_links.txt
mogptw.egg-info/requires.txt
mogptw.egg-info/top_level.txt